torchrun/__init__.py
torchrun/cli.py
torchrun/compat.py
torchrun/config.py
torchrun/deploy.py
torchrun/detect.py
torchrun/kube.py
torchrun/torch_shim.py
torchrun-0.2.9.dist-info/METADATA
torchrun-0.2.9.dist-info/WHEEL
torchrun-0.2.9.dist-info/entry_points.txt
torchrun-0.2.9.dist-info/top_level.txt
torchrun-0.2.9.dist-info/RECORD
