Metadata-Version: 2.1
Name: torchrun
Version: 0.2.9
Summary: Drop-in ROCm-native CLI for PyTorch + Kubernetes inference
Home-page: https://github.com/your-org/torchrun
Author: Ashish T
Classifier: Programming Language :: Python :: 3
Classifier: License :: OSI Approved :: MIT License
Requires-Dist: kubernetes
Requires-Dist: typer[all]
Requires-Dist: pyyaml
Requires-Dist: transformers
Requires-Dist: torch
Requires-Dist: fastapi
Requires-Dist: uvicorn
